mragent/LLM.py
mragent/__init__.py
mragent/agent_tool.py
mragent/agent_workflow.py
mragent/agent_workflow_OE.py
mragent/template_text.py
mragent-0.2.5.dist-info/LICENSE
mragent-0.2.5.dist-info/METADATA
mragent-0.2.5.dist-info/WHEEL
mragent-0.2.5.dist-info/RECORD
