Metadata-Version: 2.3
Name: mragent
Version: 0.2.5
Summary: MRAgent: An LLM-based Automated Agent for Causal Knowledge Discovery in Disease via Mendelian Randomization
Author: XU WEI
Author-email: xuwei_chn@foxmail.com
Requires-Python: >=3.9, !=2.7.*, !=3.0.*, !=3.1.*, !=3.2.*, !=3.3.*, !=3.4.*, !=3.5.*, !=3.6.*, !=3.7.*, !=3.8.*
Classifier: Programming Language :: Python :: 3
Classifier: Programming Language :: Python :: 3.9
Classifier: Programming Language :: Python :: 3.10
Classifier: Programming Language :: Python :: 3.11
Classifier: Programming Language :: Python :: 3.12
Classifier: Programming Language :: Python :: 3.13
Requires-Dist: biopython (>=1.82,<2.0)
Requires-Dist: bs4 (>=0.0.1,<0.0.2)
Requires-Dist: numpy (>=1.19.5,<2.0.0)
Requires-Dist: ollama (>=0.1.8,<0.2.0)
Requires-Dist: openai (>=1.6.1,<2.0.0)
Requires-Dist: pandas (>=1.4.2,<2.0.0)
Requires-Dist: pypdf2 (>=3.0.1,<4.0.0)
Requires-Dist: reportlab (>=4.0.9,<5.0.0)
Requires-Dist: requests (>=2.27.1,<3.0.0)
